qgis_deployment_toolbelt/__about__.py
qgis_deployment_toolbelt/__init__.py
qgis_deployment_toolbelt/_version.py
qgis_deployment_toolbelt/cli.py
qgis_deployment_toolbelt/constants.py
qgis_deployment_toolbelt/exceptions.py
qgis_deployment_toolbelt/commands/__init__.py
qgis_deployment_toolbelt/commands/cmd_rules_context.py
qgis_deployment_toolbelt/commands/deployment.py
qgis_deployment_toolbelt/commands/upgrade.py
qgis_deployment_toolbelt/jobs/__init__.py
qgis_deployment_toolbelt/jobs/generic_job.py
qgis_deployment_toolbelt/jobs/job_default_profile_setter.py
qgis_deployment_toolbelt/jobs/job_environment_variables.py
qgis_deployment_toolbelt/jobs/job_plugins_downloader.py
qgis_deployment_toolbelt/jobs/job_plugins_synchronizer.py
qgis_deployment_toolbelt/jobs/job_profiles_downloader.py
qgis_deployment_toolbelt/jobs/job_profiles_synchronizer.py
qgis_deployment_toolbelt/jobs/job_qgis_installation_finder.py
qgis_deployment_toolbelt/jobs/job_shortcuts.py
qgis_deployment_toolbelt/jobs/job_splash_screen.py
qgis_deployment_toolbelt/jobs/orchestrator.py
qgis_deployment_toolbelt/plugins/__init__.py
qgis_deployment_toolbelt/plugins/plugin.py
qgis_deployment_toolbelt/profiles/__init__.py
qgis_deployment_toolbelt/profiles/local_git_handler.py
qgis_deployment_toolbelt/profiles/profiles_handler_base.py
qgis_deployment_toolbelt/profiles/qdt_profile.py
qgis_deployment_toolbelt/profiles/qgis_ini_handler.py
qgis_deployment_toolbelt/profiles/remote_git_handler.py
qgis_deployment_toolbelt/profiles/remote_http_handler.py
qgis_deployment_toolbelt/profiles/rules_context.py
qgis_deployment_toolbelt/scenarios/__init__.py
qgis_deployment_toolbelt/scenarios/scenario_reader.py
qgis_deployment_toolbelt/shortcuts/__init__.py
qgis_deployment_toolbelt/shortcuts/icon_converter.py
qgis_deployment_toolbelt/shortcuts/shortcut_freedesktop.template
qgis_deployment_toolbelt/shortcuts/shortcuts_handler.py
qgis_deployment_toolbelt/utils/__init__.py
qgis_deployment_toolbelt/utils/bouncer.py
qgis_deployment_toolbelt-0.40.0.dist-info/licenses/LICENSE
qgis_deployment_toolbelt-0.40.0.dist-info/METADATA
qgis_deployment_toolbelt-0.40.0.dist-info/WHEEL
qgis_deployment_toolbelt-0.40.0.dist-info/entry_points.txt
qgis_deployment_toolbelt-0.40.0.dist-info/top_level.txt
qgis_deployment_toolbelt-0.40.0.dist-info/RECORD
