Metadata-Version: 2.4
Name: qgis-deployment-toolbelt
Version: 0.40.0
Summary: QGIS deployment toolbelt is a CLI (Command Line Interface) to perform redundant operations after a QGIS deployment, managing QGIS profiles, plugins, environment variables, start menu / desktop shortcuts and many things to rationalize your QGIS installations.
Author-email: "Julien Moura (Oslandia)" <qgis+qdt@oslandia.com>
Maintainer-email: "Julien Moura (Oslandia)" <qgis+qdt@oslandia.com>, "Jean-Marie Kerloch (Oslandia)" <qgis+qdt@oslandia.com>, "Nicolas Godet (ISL)" <nicolas.godet@outlook.fr>
License-Expression: Apache-2.0
Project-URL: Changelog, https://github.com/qgis-deployment/qgis-deployment-toolbelt-cli/blob/main/CHANGELOG.md
Project-URL: Documentation, https://qgis-deployment.github.io/qgis-deployment-toolbelt-cli/
Project-URL: Homepage, https://qgis-deployment.github.io/qgis-deployment-toolbelt-cli/
Project-URL: Issues, https://github.com/qgis-deployment/qgis-deployment-toolbelt-cli/issues
Project-URL: releasenotes, https://github.com/qgis-deployment/qgis-deployment-toolbelt-cli/releases/latest
Project-URL: Source, https://github.com/qgis-deployment/qgis-deployment-toolbelt-cli.git
Keywords: GIS,QGIS,cli,deployment,profiles,qdt
Classifier: Development Status :: 4 - Beta
Classifier: Intended Audience :: Information Technology
Classifier: Operating System :: Microsoft :: Windows :: Windows 10
Classifier: Operating System :: Microsoft :: Windows :: Windows 11
Classifier: Operating System :: OS Independent
Classifier: Programming Language :: Python :: 3
Classifier: Programming Language :: Python :: 3.10
Classifier: Programming Language :: Python :: 3.11
Classifier: Programming Language :: Python :: 3.12
Classifier: Programming Language :: Python :: 3.13
Classifier: Topic :: Scientific/Engineering :: GIS
Classifier: Topic :: System :: Installation/Setup
Requires-Python: <4,>=3.10
License-File: LICENSE
Requires-Dist: distro==1.9.*; sys_platform == "linux"
Requires-Dist: dulwich<0.24.7,>=0.24.1
Requires-Dist: giturlparse<0.13,>=0.12
Requires-Dist: imagesize<1.5,>=1.4
Requires-Dist: packaging<26,>=22
Requires-Dist: pypac<1,>=0.16.3
Requires-Dist: python-rule-engine<1.1,>=0.5
Requires-Dist: python-win-ad==0.6.2; sys_platform == "win32"
Requires-Dist: pywin32==311; sys_platform == "win32"
Requires-Dist: pyyaml<7,>=5.4
Requires-Dist: requests<3,>=2.32.3
Requires-Dist: truststore<1,>=0.10.1
Provides-Extra: dev
Requires-Dist: ruff>=0.13.1; extra == "dev"
Requires-Dist: pre-commit<5,>=4; extra == "dev"
Provides-Extra: doc
Requires-Dist: furo>=2024; extra == "doc"
Requires-Dist: matplotlib<4,>=3.8.2; extra == "doc"
Requires-Dist: myst-parser[linkify]>=2; extra == "doc"
Requires-Dist: sphinx-argparse-cli>=1.19; extra == "doc"
Requires-Dist: sphinx-autobuild>=2024; extra == "doc"
Requires-Dist: sphinx-copybutton<1; extra == "doc"
Requires-Dist: sphinx-design<1,>=0.5; extra == "doc"
Requires-Dist: sphinx-sitemap<3,>=2.4; extra == "doc"
Requires-Dist: sphinxcontrib-mermaid>=1; extra == "doc"
Requires-Dist: sphinxext-opengraph>=0.10; extra == "doc"
Provides-Extra: packaging
Requires-Dist: pyinstaller<6.17,>=6.13; extra == "packaging"
Requires-Dist: pyinstaller-hooks-contrib==2025.*; extra == "packaging"
Requires-Dist: pypiwin32==223; sys_platform == "win32" and extra == "packaging"
Provides-Extra: security
Requires-Dist: bandit<2,>=1.8.3; extra == "security"
Requires-Dist: safety<4,>=3.3.1; extra == "security"
Provides-Extra: test
Requires-Dist: GitPython<3.2,>=3.1; extra == "test"
Requires-Dist: Pillow<12.1,>=10.4.0; extra == "test"
Requires-Dist: pytest-cov<8,>=4; extra == "test"
Requires-Dist: validators<0.36,>=0.29.0; extra == "test"
Dynamic: license-file
